{
	"backtrace" : 3,
	"backtraceGraph" : 
	{
		"commands" : 
		[
			"add_custom_target",
			"add_llvm_install_targets",
			"add_clang_tool"
		],
		"files" : 
		[
			"cmake/modules/AddLLVM.cmake",
			"tools/clang/cmake/modules/AddClang.cmake",
			"tools/clang/tools/clang-rename/CMakeLists.txt"
		],
		"nodes" : 
		[
			{
				"file" : 2
			},
			{
				"command" : 2,
				"file" : 2,
				"line" : 6,
				"parent" : 0
			},
			{
				"command" : 1,
				"file" : 1,
				"line" : 148,
				"parent" : 1
			},
			{
				"command" : 0,
				"file" : 0,
				"line" : 588,
				"parent" : 2
			}
		]
	},
	"dependencies" : 
	[
		{
			"id" : "clang-rename::@cc7e808ddbabd895664b"
		}
	],
	"id" : "install-clang-rename-stripped::@cc7e808ddbabd895664b",
	"name" : "install-clang-rename-stripped",
	"paths" : 
	{
		"build" : "tools/clang/tools/clang-rename",
		"source" : "tools/clang/tools/clang-rename"
	},
	"sourceGroups" : 
	[
		{
			"name" : "",
			"sourceIndexes" : 
			[
				0
			]
		},
		{
			"name" : "CMake Rules",
			"sourceIndexes" : 
			[
				1
			]
		}
	],
	"sources" : 
	[
		{
			"backtrace" : 3,
			"isGenerated" : true,
			"path" : "cmake-build-debug/tools/clang/tools/clang-rename/CMakeFiles/install-clang-rename-stripped",
			"sourceGroupIndex" : 0
		},
		{
			"backtrace" : 0,
			"isGenerated" : true,
			"path" : "cmake-build-debug/tools/clang/tools/clang-rename/CMakeFiles/install-clang-rename-stripped.rule",
			"sourceGroupIndex" : 1
		}
	],
	"type" : "UTILITY"
}
