{
	"backtrace" : 1,
	"backtraceGraph" : 
	{
		"commands" : 
		[
			"add_custom_target"
		],
		"files" : 
		[
			"projects/compiler-rt/lib/tsan/CMakeLists.txt"
		],
		"nodes" : 
		[
			{
				"file" : 0
			},
			{
				"command" : 0,
				"file" : 0,
				"line" : 172,
				"parent" : 0
			}
		]
	},
	"dependencies" : 
	[
		{
			"id" : "clang_rt.tsan-x86_64::@eb2e153928c6854e71ad"
		}
	],
	"id" : "GotsanRuntimeCheck::@eb2e153928c6854e71ad",
	"name" : "GotsanRuntimeCheck",
	"paths" : 
	{
		"build" : "projects/compiler-rt/lib/tsan",
		"source" : "projects/compiler-rt/lib/tsan"
	},
	"sourceGroups" : 
	[
		{
			"name" : "",
			"sourceIndexes" : 
			[
				0
			]
		},
		{
			"name" : "CMake Rules",
			"sourceIndexes" : 
			[
				1
			]
		}
	],
	"sources" : 
	[
		{
			"backtrace" : 1,
			"isGenerated" : true,
			"path" : "cmake-build-debug/projects/compiler-rt/lib/tsan/CMakeFiles/GotsanRuntimeCheck",
			"sourceGroupIndex" : 0
		},
		{
			"backtrace" : 0,
			"isGenerated" : true,
			"path" : "cmake-build-debug/projects/compiler-rt/lib/tsan/CMakeFiles/GotsanRuntimeCheck.rule",
			"sourceGroupIndex" : 1
		}
	],
	"type" : "UTILITY"
}
